ds_user/__init__.py
ds_user/client.py
ds_user-0.0.5.dist-info/LICENSE
ds_user-0.0.5.dist-info/METADATA
ds_user-0.0.5.dist-info/WHEEL
ds_user-0.0.5.dist-info/top_level.txt
ds_user-0.0.5.dist-info/RECORD
