Metadata-Version: 2.1
Name: ds_user
Version: 0.0.5
Summary: This library will make it easier to manage Discord accounts with an account token!
Author-email: selfsff <example@gmail.com>
Project-URL: Homepage, https://www.google.com
Project-URL: Issues, https://www.google.com
Classifier: Programming Language :: Python :: 3
Classifier: License :: OSI Approved :: MIT License
Classifier: Operating System :: OS Independent
Requires-Python: >=3.10.0
License-File: LICENSE
